pythonscholar_replace_space/__init__.py
pythonscholar_replace_space-0.1.0.dist-info/METADATA
pythonscholar_replace_space-0.1.0.dist-info/WHEEL
pythonscholar_replace_space-0.1.0.dist-info/top_level.txt
pythonscholar_replace_space-0.1.0.dist-info/RECORD
