Metadata-Version: 2.1
Name: pythonscholar-replace-space
Version: 0.1.0
Summary: A Python package to replace spaces with underscores in a string.
Home-page: https://github.com/khushaljethava/pythonscholar_replace_space
Author: Khushal Jethava
Classifier: License :: OSI Approved :: MIT License
Classifier: Programming Language :: Python :: 3
Classifier: Programming Language :: Python :: 3.6
Classifier: Programming Language :: Python :: 3.7
Classifier: Programming Language :: Python :: 3.8
